spyder_coala/__init__.py
spyder_coala/_version.py
spyder_coala/coalaplugin.py
spyder_coala/confpage.py
spyder_coala/widgets/__init__.py
spyder_coala/widgets/coalagui.py
spyder_coala/widgets/run_coala.py
spyder_coala-0.0.1.dev0.dist-info/LICENSE
spyder_coala-0.0.1.dev0.dist-info/METADATA
spyder_coala-0.0.1.dev0.dist-info/WHEEL
spyder_coala-0.0.1.dev0.dist-info/top_level.txt
spyder_coala-0.0.1.dev0.dist-info/RECORD
